match_diff_lines.py
match_diff_lines-0.2.0.dist-info/LICENSE
match_diff_lines-0.2.0.dist-info/METADATA
match_diff_lines-0.2.0.dist-info/WHEEL
match_diff_lines-0.2.0.dist-info/entry_points.txt
match_diff_lines-0.2.0.dist-info/top_level.txt
match_diff_lines-0.2.0.dist-info/RECORD
