Metadata-Version: 2.1
Name: match-diff-lines
Version: 0.2.0
Maintainer-email: Florian Schulze <mail@florian-schulze.net>
License: Permission is hereby granted, free of charge, to any person obtaining a copy of
Project-URL: Bug Tracker, https://github.com/fschulze/match-diff-lines/issues
Project-URL: Changelog, https://github.com/fschulze/match-diff-lines/blob/main/CHANGELOG.rst
Project-URL: Homepage, https://github.com/fschulze/match-diff-lines
Project-URL: Source Code, https://github.com/fschulze/match-diff-lines
Requires-Python: >=3.9
License-File: LICENSE
